hestia/__init__.py
hestia/clustering.py
hestia/dataset_generator.py
hestia/partition.py
hestia/reduction.py
hestia/similarity.py
hestia/utils/__init__.py
hestia/utils/bulk_similarity_metrics.py
hestia/utils/dataset_utils.py
hestia/utils/file_format.py
hestia/utils/fingerprints.py
hestia/utils/graph_part_utils.py
hestia/utils/label_balance.py
hestia/utils/mmseqs_fake_prefilter.sh
hestia_good-1.0.4.data/data/mmseqs_fake_prefilter.sh
hestia_good-1.0.4.dist-info/licenses/LICENSE
hestia_good-1.0.4.dist-info/METADATA
hestia_good-1.0.4.dist-info/WHEEL
hestia_good-1.0.4.dist-info/top_level.txt
hestia_good-1.0.4.dist-info/RECORD
