Metadata-Version: 2.4
Name: hestia-good
Version: 1.0.4
Summary: Independent evaluation set construction for trustworthy ML models in biochemistry
Home-page: https://github.com/IBM/Hestia-GOOD
Author: Raul Fernandez-Diaz
Author-email: raul.fernandezdiaz@ucdconnect.ie
License: MIT
Keywords: hestia
Requires-Python: >=3.9
License-File: LICENSE
Requires-Dist: scipy
Requires-Dist: scikit-learn
Requires-Dist: pandas
Requires-Dist: polars
Requires-Dist: numpy
Requires-Dist: tqdm
Requires-Dist: pyarrow
Dynamic: author
Dynamic: author-email
Dynamic: description
Dynamic: description-content-type
Dynamic: home-page
Dynamic: keywords
Dynamic: license
Dynamic: license-file
Dynamic: requires-dist
Dynamic: requires-python
Dynamic: summary
